{"PlayList":[{"fileName":"wda","MusicList":[{"absolutePath":"C:\\Users\\black\\music\\music\\glow.mp3","fileName":"glow.mp3"},{"absolutePath":"C:\\Users\\black\\music\\music\\GOD EATER No way back ~Out of my way.mp3","fileName":"GOD EATER No way back ~Out of my way.mp3"},{"absolutePath":"C:\\Users\\black\\music\\music\\God Eater 2 Game Opening Full - FATE.mp3","fileName":"God Eater 2 Game Opening Full - FATE.mp3"},{"absolutePath":"C:\\Users\\black\\music\\Walkure\\絶対零度ノヴァスティック2 (online-audio-converter.com).mp3","fileName":"絶対零度ノヴァスティック2 (online-audio-converter.com).mp3"}]},{"fileName":"egoist","MusicList":[{"absolutePath":"C:\\Users\\black\\music\\music\\EGOIST\\KABANERI OF THE IRON FORTRESS\\It's all about you.m4a","fileName":"It's all about you.m4a"},{"absolutePath":"C:\\Users\\black\\music\\music\\EGOIST\\KABANERI OF THE IRON FORTRESS\\KABANERI OF THE IRON FORTRESS.m4a","fileName":"KABANERI OF THE IRON FORTRESS.m4a"},{"absolutePath":"C:\\Users\\black\\music\\music\\EGOIST\\The Everlasting Guilty Crown\\キミソラキセキ.m4a","fileName":"キミソラキセキ.m4a"},{"absolutePath":"C:\\Users\\black\\music\\music\\EGOIST\\Welcome to the _fam\\Welcome to the _fam.m4a","fileName":"Welcome to the _fam.m4a"},{"absolutePath":"C:\\Users\\black\\music\\music\\EGOIST\\Fallen\\Fallen.m4a","fileName":"Fallen.m4a"}]},{"fileName":"GodEater","MusicList":[]},{"fileName":"www","MusicList":[]}],"Volume":21.0}